worklog/__init__.py
worklog/__main__.py
worklog/breaks.py
worklog/config.cfg
worklog/constants.py
worklog/dispatcher.py
worklog/errors.py
worklog/log.py
worklog/parser.py
worklog/tests/__init__.py
worklog/tests/test_breaks.py
worklog/tests/test_dispatcher.py
worklog/tests/test_log.py
worklog/tests/test_parser.py
worklog/tests/snapshots/__init__.py
worklog/tests/snapshots/snap_test_log.py
worklog/tests/utils/__init__.py
worklog/tests/utils/test_formatting.py
worklog/tests/utils/test_logger.py
worklog/tests/utils/test_pager.py
worklog/tests/utils/test_schema.py
worklog/tests/utils/test_session.py
worklog/tests/utils/test_tasks.py
worklog/tests/utils/test_time.py
worklog/utils/__init__.py
worklog/utils/formatting.py
worklog/utils/logger.py
worklog/utils/pager.py
worklog/utils/schema.py
worklog/utils/session.py
worklog/utils/tasks.py
worklog/utils/time.py
dcs_worklog-0.0.38.dist-info/LICENSE
dcs_worklog-0.0.38.dist-info/METADATA
dcs_worklog-0.0.38.dist-info/WHEEL
dcs_worklog-0.0.38.dist-info/entry_points.txt
dcs_worklog-0.0.38.dist-info/top_level.txt
dcs_worklog-0.0.38.dist-info/RECORD
