Metadata-Version: 2.1
Name: dcs-worklog
Version: 0.0.38
Summary: Simple CLI tool to log work and projects
Home-page: https://github.com/dotcs/worklog
Author: Fabian Mueller
Author-email: repository@dotcs.me
License: GPLv3
Platform: UNKNOWN
Classifier: Development Status :: 3 - Alpha
Classifier: Environment :: Console
Classifier: License :: OSI Approved :: GNU General Public License v3 (GPLv3)
Classifier: Natural Language :: English
Classifier: Operating System :: OS Independent
Classifier: Programming Language :: Python :: 3
Classifier: Topic :: Office/Business
Requires-Python: >=3.6
Requires-Dist: pandas
Provides-Extra: develop
Requires-Dist: pytest ; extra == 'develop'
Requires-Dist: pytest-cov ; extra == 'develop'
Requires-Dist: snapshottest ; extra == 'develop'
Requires-Dist: sphinx (<4,>=3.2.0) ; extra == 'develop'
Requires-Dist: sphinx-rtd-theme ; extra == 'develop'
